jax_bandflux-0.3.11.dist-info/licenses/LICENSE
jax_supernovae/__init__.py
jax_supernovae/bandpasses.py
jax_supernovae/constants.py
jax_supernovae/data.py
jax_supernovae/dust.py
jax_supernovae/salt3.py
jax_supernovae/source.py
jax_supernovae/timeseries.py
jax_supernovae/utils.py
jax_supernovae/data/example_template.phot
jax_supernovae/data/redshifts.dat
jax_supernovae/data/19dwz/J_1D3.phot
jax_supernovae/data/19dwz/J_2D.phot
jax_supernovae/data/19dwz/all.phot
jax_supernovae/data/19dwz/ebv_fits.dat
jax_supernovae/data/19dwz/max_fits.dat
jax_supernovae/data/19dwz/salt_fits.dat
jax_supernovae/data/20aai/all.phot
jax_supernovae/data/20aai/ebv_fits.dat
jax_supernovae/data/20aai/max_fits.dat
jax_supernovae/data/20aai/salt_fits.dat
jax_supernovae/data/models/salt3-nir/salt3nir-p22/._SALT3.INFO
jax_supernovae/data/models/salt3-nir/salt3nir-p22/._salt3_color_correction.dat
jax_supernovae/data/models/salt3-nir/salt3nir-p22/._salt3_color_dispersion.dat
jax_supernovae/data/models/salt3-nir/salt3nir-p22/._salt3_lc_covariance_01.dat
jax_supernovae/data/models/salt3-nir/salt3nir-p22/._salt3_lc_variance_0.dat
jax_supernovae/data/models/salt3-nir/salt3nir-p22/._salt3_lc_variance_1.dat
jax_supernovae/data/models/salt3-nir/salt3nir-p22/._salt3_template_0.dat
jax_supernovae/data/models/salt3-nir/salt3nir-p22/._salt3_template_1.dat
jax_supernovae/data/models/salt3-nir/salt3nir-p22/SALT3.INFO
jax_supernovae/data/models/salt3-nir/salt3nir-p22/salt3_color_correction.dat
jax_supernovae/data/models/salt3-nir/salt3nir-p22/salt3_color_dispersion.dat
jax_supernovae/data/models/salt3-nir/salt3nir-p22/salt3_lc_covariance_01.dat
jax_supernovae/data/models/salt3-nir/salt3nir-p22/salt3_lc_variance_0.dat
jax_supernovae/data/models/salt3-nir/salt3nir-p22/salt3_lc_variance_1.dat
jax_supernovae/data/models/salt3-nir/salt3nir-p22/salt3_template_0.dat
jax_supernovae/data/models/salt3-nir/salt3nir-p22/salt3_template_1.dat
jax_supernovae/sncosmo-modelfiles/bandpasses/2mass/2mass.H
jax_supernovae/sncosmo-modelfiles/bandpasses/atlas/Atlas.Cyan
jax_bandflux-0.3.11.dist-info/METADATA
jax_bandflux-0.3.11.dist-info/WHEEL
jax_bandflux-0.3.11.dist-info/top_level.txt
jax_bandflux-0.3.11.dist-info/RECORD
