Metadata-Version: 2.4
Name: jax-bandflux
Version: 0.3.11
Summary: JAX-based supernova bandflux modelling with SALT3
Author-email: Samuel Alan Kossoff Leeney <sakl2@cam.ac.uk>
License: MIT
Keywords: supernova,jax,sncosmo,astronomy,salt3
Classifier: Development Status :: 3 - Alpha
Classifier: Intended Audience :: Science/Research
Classifier: License :: OSI Approved :: MIT License
Classifier: Programming Language :: Python :: 3
Classifier: Programming Language :: Python :: 3 :: Only
Classifier: Programming Language :: Python :: 3.10
Classifier: Topic :: Scientific/Engineering :: Astronomy
Requires-Python: >=3.10
License-File: LICENSE
Requires-Dist: numpy>=1.24.0
Requires-Dist: jax>=0.4.20
Requires-Dist: sncosmo>=2.9.0
Requires-Dist: astropy>=5.0.0
Requires-Dist: pyyaml>=6.0.0
Requires-Dist: matplotlib
Requires-Dist: tqdm
Requires-Dist: requests
Provides-Extra: docs
Requires-Dist: sphinx>=5.0.0; extra == "docs"
Requires-Dist: sphinx-rtd-theme>=1.0.0; extra == "docs"
Requires-Dist: sphinxcontrib-mermaid>=0.7.0; extra == "docs"
Requires-Dist: sphinx-autodoc-typehints>=1.12.0; extra == "docs"
Provides-Extra: dev
Requires-Dist: pytest>=7.0; extra == "dev"
Requires-Dist: pytest-cov>=2.0; extra == "dev"
Requires-Dist: black>=22.0; extra == "dev"
Requires-Dist: isort>=5.0; extra == "dev"
Provides-Extra: nested
Requires-Dist: anesthetic; extra == "nested"
Requires-Dist: blackjax>=1.0.0; extra == "nested"
Requires-Dist: distrax; extra == "nested"
Provides-Extra: cuda12
Requires-Dist: jax[cuda12]>=0.4.20; extra == "cuda12"
Dynamic: license-file
